toai/__init__.py
toai/imports.py
toai/data/DataBundle.py
toai/data/DataParams.py
toai/data/__init__.py
toai/data/utils.py
toai/encode/CategoricalEncoder.py
toai/encode/__init__.py
toai/extract/Extractor.py
toai/extract/__init__.py
toai/inpute/CategoricalInputer.py
toai/inpute/ImageInputer.py
toai/inpute/NumericInputer.py
toai/inpute/__init__.py
toai/metrics/__init__.py
toai/metrics/error_rate.py
toai/metrics/rmse.py
toai/preprocessing/LogTransformer.py
toai/preprocessing/__init__.py
toai/tensorflow/DataContainer.py
toai/tensorflow/ImageAugmentor.py
toai/tensorflow/ImageDataBundle.py
toai/tensorflow/ImageDataContainer.py
toai/tensorflow/ImageLearner.py
toai/tensorflow/ImageParser.py
toai/tensorflow/ImageResizer.py
toai/tensorflow/ImageTrainer.py
toai/tensorflow/ImageTrainingCycle.py
toai/tensorflow/LearningRateFinder.py
toai/tensorflow/__init__.py
toai/tensorflow/load_model.py
toai/tensorflow/save_model.py
toai/utils/__init__.py
toai/utils/download_file.py
toai/utils/load_file.py
toai/utils/save_file.py
toai/utils/unzip.py
toai-0.6.5.dist-info/LICENSE
toai-0.6.5.dist-info/METADATA
toai-0.6.5.dist-info/WHEEL
toai-0.6.5.dist-info/top_level.txt
toai-0.6.5.dist-info/RECORD
